legendtestdata/__init__.py
legendtestdata/_version.py
legendtestdata/core.py
pylegendtestdata-0.6.0.dist-info/licenses/LICENSE
pylegendtestdata-0.6.0.dist-info/METADATA
pylegendtestdata-0.6.0.dist-info/WHEEL
pylegendtestdata-0.6.0.dist-info/top_level.txt
pylegendtestdata-0.6.0.dist-info/RECORD
